README.md
setup.cfg
setup.py
chromedriver_autodownloader/__init__.py
chromedriver_autodownloader/chromedriver_downloader.py
chromedriver_autodownloader.egg-info/PKG-INFO
chromedriver_autodownloader.egg-info/SOURCES.txt
chromedriver_autodownloader.egg-info/dependency_links.txt
chromedriver_autodownloader.egg-info/top_level.txt