Metadata-Version: 2.1
Name: chromedriver-autodownloader
Version: 0.2.0
Summary: UNKNOWN
Home-page: https://github.com/umardy/chromedriver-autodownloader
Author: Umardy
Author-email: umardev004@gmail.com
License: Apache Software License (http://www.apache.org/licenses/LICENSE-2.0)
Keywords: automatic chromedriver downloader
Platform: UNKNOWN
Classifier: License :: OSI Approved :: Apache Software License
Classifier: Programming Language :: Python :: 3
Classifier: Programming Language :: Python :: 3.6
Classifier: Programming Language :: Python :: 3.7
Classifier: Programming Language :: Python :: 3.8
Classifier: Programming Language :: Python :: 3.9
